natnet/__init__.py
natnet/data_descriptions.py
natnet/data_frame.py
natnet/data_types.py
natnet/event.py
natnet/exceptions.py
natnet/nat_net_client.py
natnet/packet_buffer.py
natnet/packet_component.py
natnet/server_info.py
natnet/version.py
natnet-0.2.0.dist-info/licenses/LICENSE
natnet-0.2.0.dist-info/METADATA
natnet-0.2.0.dist-info/WHEEL
natnet-0.2.0.dist-info/top_level.txt
natnet-0.2.0.dist-info/RECORD
