Metadata-Version: 2.4
Name: natnet
Version: 0.2.0
Summary: Python client for Optitrack NatNet streams.
Author-email: Tim Schneider <tim@robot-learning.de>
License: MIT
Project-URL: Homepage, https://github.com/TimSchneider42/python-natnet-client
Project-URL: Bug Tracker, https://github.com/TimSchneider42/python-natnet-client/issues
Classifier: Programming Language :: Python :: 3
Classifier: License :: OSI Approved :: MIT License
Classifier: Operating System :: OS Independent
Requires-Python: >=3.6
License-File: LICENSE
Dynamic: license-file
